flask_ujson/__init__.py
flask_ujson-1.0.6.dist-info/LICENSE
flask_ujson-1.0.6.dist-info/WHEEL
flask_ujson-1.0.6.dist-info/METADATA
flask_ujson-1.0.6.dist-info/RECORD
