Metadata-Version: 2.1
Name: flask-ujson
Version: 1.0.6
Summary: Flask with UltraJSON.
Author-email: David Carmichael <david@uilix.com>
Requires-Python: >=3.8
Requires-Dist: ujson >= 5.8.0
Requires-Dist: flask >= 3.0.0
Project-URL: Home, https://github.com/CheeseCake87/flask-ujson
